{"img/bk1.png": {"Account_Number": "987-654-321", "Statement_Date": "2024-05-01", "Period_Covered": "2024-04-01 to 2024-04-30", "name": "Alice Johnson", "address_line1": "789 Liberty Ave, Unit 2", "address_line2": "Springfield, IL 62704", "Opening_Balance": "200,000.00", "Total_Credit_Amount": "65,000.00", "Total_Debit_Amount": "15,000.00", "Closing_Balance": "250,000.00", "Account_Type": "Checking", "Number_Transactions": "8", "transactions": [{"Date": "2024-04-02", "Description": "Grocery Store", "Credit": "-", "Debit": "-$350.00", "Balance": "$199,650.00"}, {"Date": "2024-04-05", "Description": "Direct Deposit", "Credit": "$50,000.00", "Debit": "-", "Balance": "$249,650.00"}, {"Date": "2024-04-07", "Description": "Pharmacy", "Credit": "-", "Debit": "-$120.00", "Balance": "$249,530.00"}, {"Date": "2024-04-10", "Description": "Utility Bill", "Credit": "-", "Debit": "-$200.00", "Balance": "$249,330.00"}, {"Date": "2024-04-15", "Description": "Online Shopping", "Credit": "-", "Debit": "-$1,330.00", "Balance": "$248,000.00"}, {"Date": "2024-04-18", "Description": "Car Loan Payment", "Credit": "-", "Debit": "-$1,000.00", "Balance": "$247,000.00"}, {"Date": "2024-04-22", "Description": "Direct Deposit", "Credit": "$15,000.00", "Debit": "-", "Balance": "$262,000.00"}, {"Date": "2024-04-25", "Description": "Dining Out", "Credit": "-", "Debit": "-$150.00", "Balance": "$261,850.00"}]}, "img/bk2.png": {"Account_Number": "456-789-123", "Statement_Date": "2024-06-01", "Period_Covered": "2024-05-01 to 2024-05-31", "name": "Michael Smith", "address_line1": "1122 Freedom Rd, Apt 305", "address_line2": "Nashville, TN 37209", "Opening_Balance": "120,000.00", "Total_Credit_Amount": "30,000.00", "Total_Debit_Amount": "10,000.00", "Closing_Balance": "140,000.00", "Account_Type": "Savings", "Number_Transactions": "6", "transactions": [{"Date": "2024-05-03", "Description": "Bookstore Purchase", "Credit": "-", "Debit": "-$200.00", "Balance": "$119,800.00"}, {"Date": "2024-05-06", "Description": "Salary Deposit", "Credit": "$20,000.00", "Debit": "-", "Balance": "$139,800.00"}, {"Date": "2024-05-10", "Description": "Electric Bill", "Credit": "-", "Debit": "-$150.00", "Balance": "$139,650.00"}, {"Date": "2024-05-15", "Description": "Gym Membership", "Credit": "-", "Debit": "-$50.00", "Balance": "$139,600.00"}, {"Date": "2024-05-20", "Description": "Freelance Payment", "Credit": "$10,000.00", "Debit": "-", "Balance": "$149,600.00"}, {"Date": "2024-05-25", "Description": "Car Insurance", "Credit": "-", "Debit": "-$9,600.00", "Balance": "$140,000.00"}]}, "img/bk3.png": {"Account_Number": "321-987-654", "Statement_Date": "2024-07-01", "Period_Covered": "2024-06-01 to 2024-06-30", "name": "Emma Thompson", "address_line1": "3342 Peaceful Ln, Suite 210", "address_line2": "Rochester, NY 14620", "Opening_Balance": "85,000.00", "Total_Credit_Amount": "45,000.00", "Total_Debit_Amount": "20,000.00", "Closing_Balance": "110,000.00", "Account_Type": "Checking", "Number_Transactions": "7", "transactions": [{"Date": "2024-06-02", "Description": "Local Market", "Credit": "-", "Debit": "-$500.00", "Balance": "$84,500.00"}, {"Date": "2024-06-05", "Description": "Monthly Salary", "Credit": "$40,000.00", "Debit": "-", "Balance": "$124,500.00"}, {"Date": "2024-06-10", "Description": "Mortgage Payment", "Credit": "-", "Debit": "-$15,000.00", "Balance": "$109,500.00"}, {"Date": "2024-06-15", "Description": "Car Maintenance", "Credit": "-", "Debit": "-$1,000.00", "Balance": "$108,500.00"}, {"Date": "2024-06-20", "Description": "Health Insurance", "Credit": "-", "Debit": "-$3,500.00", "Balance": "$105,000.00"}, {"Date": "2024-06-25", "Description": "Freelance Income", "Credit": "$5,000.00", "Debit": "-", "Balance": "$110,000.00"}]}, "img/bk4.png": {"Account_Number": "852-963-741", "Statement_Date": "2024-08-01", "Period_Covered": "2024-07-01 to 2024-07-31", "name": "Sophia Martinez", "address_line1": "6789 Dreamland Ave, Apt 101", "address_line2": "Orlando, FL 32801", "Opening_Balance": "95,500.00", "Total_Credit_Amount": "20,000.00", "Total_Debit_Amount": "8,000.00", "Closing_Balance": "107,500.00", "Account_Type": "Savings", "Number_Transactions": "5", "transactions": [{"Date": "2024-07-03", "Description": "Grocery Shopping", "Credit": "-", "Debit": "-$750.00", "Balance": "$94,750.00"}, {"Date": "2024-07-10", "Description": "Salary Deposit", "Credit": "$15,000.00", "Debit": "-", "Balance": "$109,750.00"}, {"Date": "2024-07-15", "Description": "Dental Insurance", "Credit": "-", "Debit": "-$500.00", "Balance": "$109,250.00"}, {"Date": "2024-07-20", "Description": "Home Repair Services", "Credit": "-", "Debit": "-$6,750.00", "Balance": "$102,500.00"}, {"Date": "2024-07-25", "Description": "Interest Payment", "Credit": "$5,000.00", "Debit": "-", "Balance": "$107,500.00"}]}}